{"metadata": {"dbt_schema_version": "https://schemas.getdbt.com/dbt/run-results/v6.json", "dbt_version": "1.10.5", "generated_at": "2025-10-20T06:55:10.469971Z", "invocation_id": "615a8a65-1330-40f8-87bf-e3caa7965817", "invocation_started_at": "2025-10-20T06:54:48.171363Z", "env": {}}, "results": [{"status": "pass", "timing": [{"name": "compile", "started_at": "2025-10-20T06:54:53.899662Z", "completed_at": "2025-10-20T06:54:54.046518Z"}, {"name": "execute", "started_at": "2025-10-20T06:54:54.069821Z", "completed_at": "2025-10-20T06:54:54.902453Z"}], "thread_id": "Thread-4 (worker)", "execution_time": 1.025068759918213, "adapter_response": {"_message": "SUCCESS 1", "code": "SUCCESS", "rows_affected": 1, "query_id": "01bfd4be-3202-077f-0010-8a120003442e"}, "message": null, "failures": 0, "unique_id": "test.data_pipeline.source_not_null_tpch_orders_o_orderkey.ebd571817b", "compiled": true, "compiled_code": "\n    \n    \n\n\n\nselect o_orderkey\nfrom snowflake_sample_data.tpch_sf1.orders\nwhere o_orderkey is null\n\n\n", "relation_name": null, "batch_results": null}, {"status": "pass", "timing": [{"name": "compile", "started_at": "2025-10-20T06:54:53.962626Z", "completed_at": "2025-10-20T06:54:54.046518Z"}, {"name": "execute", "started_at": "2025-10-20T06:54:54.072820Z", "completed_at": "2025-10-20T06:54:54.916342Z"}], "thread_id": "Thread-6 (worker)", "execution_time": 1.0379574298858643, "adapter_response": {"_message": "SUCCESS 1", "code": "SUCCESS", "rows_affected": 1, "query_id": "01bfd4be-3202-077f-0010-8a1200034426"}, "message": null, "failures": 0, "unique_id": "test.data_pipeline.source_unique_tpch_orders_o_orderkey.374f048af2", "compiled": true, "compiled_code": "\n    \n    \n\nselect\n    o_orderkey as unique_field,\n    count(*) as n_records\n\nfrom snowflake_sample_data.tpch_sf1.orders\nwhere o_orderkey is not null\ngroup by o_orderkey\nhaving count(*) > 1\n\n\n", "relation_name": null, "batch_results": null}, {"status": "pass", "timing": [{"name": "compile", "started_at": "2025-10-20T06:54:53.908662Z", "completed_at": "2025-10-20T06:54:54.045519Z"}, {"name": "execute", "started_at": "2025-10-20T06:54:54.048522Z", "completed_at": "2025-10-20T06:54:55.044577Z"}], "thread_id": "Thread-5 (worker)", "execution_time": 1.1671924591064453, "adapter_response": {"_message": "SUCCESS 1", "code": "SUCCESS", "rows_affected": 1, "query_id": "01bfd4be-3202-0771-0010-8a12000333ee"}, "message": null, "failures": 0, "unique_id": "test.data_pipeline.source_relationships_tpch_lineitem_l_orderkey__o_orderkey__source_tpch_orders_.f722cb898d", "compiled": true, "compiled_code": "\n    \n    \n\nwith child as (\n    select l_orderkey as from_field\n    from snowflake_sample_data.tpch_sf1.lineitem\n    where l_orderkey is not null\n),\n\nparent as (\n    select o_orderkey as to_field\n    from snowflake_sample_data.tpch_sf1.orders\n)\n\nselect\n    from_field\n\nfrom child\nleft join parent\n    on child.from_field = parent.to_field\n\nwhere parent.to_field is null\n\n\n", "relation_name": null, "batch_results": null}, {"status": "success", "timing": [{"name": "compile", "started_at": "2025-10-20T06:54:53.879381Z", "completed_at": "2025-10-20T06:54:54.000659Z"}, {"name": "execute", "started_at": "2025-10-20T06:54:54.017660Z", "completed_at": "2025-10-20T06:54:55.041453Z"}], "thread_id": "Thread-1 (worker)", "execution_time": 1.167069911956787, "adapter_response": {"_message": "SUCCESS 1", "code": "SUCCESS", "rows_affected": 1, "query_id": "01bfd4be-3202-077f-0010-8a120003442a"}, "message": "SUCCESS 1", "failures": null, "unique_id": "model.data_pipeline.stg_tpch_line_items", "compiled": true, "compiled_code": "select\n    md5(cast(coalesce(cast(l_orderkey as TEXT), '_dbt_utils_surrogate_key_null_') || '-' || coalesce(cast(l_linenumber as TEXT), '_dbt_utils_surrogate_key_null_') as TEXT)) as order_item_key,\n\tl_orderkey as order_key,\n\tl_partkey as part_key,\n\tl_linenumber as line_number,\n\tl_quantity as quantity,\n\tl_extendedprice as extended_price,\n\tl_discount as discount_percentage,\n\tl_tax as tax_rate\nfrom\n    snowflake_sample_data.tpch_sf1.lineitem", "relation_name": "dbt_db.dbt_schema.stg_tpch_line_items", "batch_results": null}, {"status": "success", "timing": [{"name": "compile", "started_at": "2025-10-20T06:54:54.923391Z", "completed_at": "2025-10-20T06:54:54.926760Z"}, {"name": "execute", "started_at": "2025-10-20T06:54:54.926760Z", "completed_at": "2025-10-20T06:54:55.940087Z"}], "thread_id": "Thread-8 (worker)", "execution_time": 1.0176975727081299, "adapter_response": {"_message": "SUCCESS 1", "code": "SUCCESS", "rows_affected": 1, "query_id": "01bfd4be-3202-0771-0010-8a12000333fa"}, "message": "SUCCESS 1", "failures": null, "unique_id": "model.data_pipeline.stg_tpch_orders", "compiled": true, "compiled_code": "select\n    o_orderkey as order_key,\n    o_custkey as customer_key,\n    o_orderstatus as status_code,\n    o_totalprice as total_price,\n    o_orderdate as order_date\nfrom\n    snowflake_sample_data.tpch_sf1.orders", "relation_name": "dbt_db.dbt_schema.stg_tpch_orders", "batch_results": null}, {"status": "success", "timing": [{"name": "compile", "started_at": "2025-10-20T06:54:53.895667Z", "completed_at": "2025-10-20T06:54:53.895667Z"}, {"name": "execute", "started_at": "2025-10-20T06:54:53.918868Z", "completed_at": "2025-10-20T06:54:56.860899Z"}], "thread_id": "Thread-2 (worker)", "execution_time": 2.9864251613616943, "adapter_response": {"_message": "INSERT 4", "code": "INSERT", "rows_affected": 4}, "message": "INSERT 4", "failures": null, "unique_id": "seed.data_pipeline.customers", "compiled": null, "compiled_code": null, "relation_name": null, "batch_results": null}, {"status": "success", "timing": [{"name": "compile", "started_at": "2025-10-20T06:54:53.895667Z", "completed_at": "2025-10-20T06:54:53.898664Z"}, {"name": "execute", "started_at": "2025-10-20T06:54:53.939379Z", "completed_at": "2025-10-20T06:54:59.072052Z"}], "thread_id": "Thread-3 (worker)", "execution_time": 5.195667266845703, "adapter_response": {"_message": "SUCCESS 0", "code": "SUCCESS", "rows_affected": 0, "query_id": "01bfd4be-3202-0771-0010-8a1200033416"}, "message": "SUCCESS 0", "failures": null, "unique_id": "snapshot.data_pipeline.customer_snapshot", "compiled": true, "compiled_code": "\n\n\n\nSELECT\n    customer_id,\n    customer_name,\n    customer_status,\n    updated_at\nFROM dbt_db.dbt_schema.customers  -- must match YAML source name\n", "relation_name": "dbt_db.snapshots.customer_snapshot", "batch_results": null}, {"status": "pass", "timing": [{"name": "compile", "started_at": "2025-10-20T06:54:59.084689Z", "completed_at": "2025-10-20T06:54:59.089908Z"}, {"name": "execute", "started_at": "2025-10-20T06:54:59.089908Z", "completed_at": "2025-10-20T06:54:59.579200Z"}], "thread_id": "Thread-5 (worker)", "execution_time": 0.49573421478271484, "adapter_response": {"_message": "SUCCESS 1", "code": "SUCCESS", "rows_affected": 1, "query_id": "01bfd4be-3202-077f-0010-8a120003444e"}, "message": null, "failures": 0, "unique_id": "test.data_pipeline.unique_current_customer", "compiled": true, "compiled_code": "-- Test: Ensure there is only one current record per customer in the snapshot\n\nSELECT \n    customer_id\nFROM dbt_db.snapshots.customer_snapshot\nWHERE dbt_valid_to IS NULL\nGROUP BY customer_id\nHAVING COUNT(*) > 1", "relation_name": null, "batch_results": null}, {"status": "pass", "timing": [{"name": "compile", "started_at": "2025-10-20T06:54:59.079463Z", "completed_at": "2025-10-20T06:54:59.087687Z"}, {"name": "execute", "started_at": "2025-10-20T06:54:59.087687Z", "completed_at": "2025-10-20T06:55:00.030203Z"}], "thread_id": "Thread-9 (worker)", "execution_time": 0.951740026473999, "adapter_response": {"_message": "SUCCESS 1", "code": "SUCCESS", "rows_affected": 1, "query_id": "01bfd4be-3202-077f-0010-8a1200034456"}, "message": null, "failures": 0, "unique_id": "test.data_pipeline.not_null_customer_snapshot_customer_id.0e40d02414", "compiled": true, "compiled_code": "\n    \n    \n\n\n\nselect customer_id\nfrom dbt_db.snapshots.customer_snapshot\nwhere customer_id is null\n\n\n", "relation_name": null, "batch_results": null}, {"status": "success", "timing": [{"name": "compile", "started_at": "2025-10-20T06:55:00.033203Z", "completed_at": "2025-10-20T06:55:00.036204Z"}, {"name": "execute", "started_at": "2025-10-20T06:55:00.037205Z", "completed_at": "2025-10-20T06:55:00.952839Z"}], "thread_id": "Thread-8 (worker)", "execution_time": 0.9216349124908447, "adapter_response": {"_message": "SUCCESS 1", "code": "SUCCESS", "rows_affected": 1, "query_id": "01bfd4be-3202-077f-0010-8a120003445a"}, "message": "SUCCESS 1", "failures": null, "unique_id": "model.data_pipeline.customer_activity", "compiled": true, "compiled_code": "-- This model demonstrates how to use snapshot data for current and historical insights\n\nWITH snapshot_data AS (\n    SELECT \n        customer_id,\n        customer_name,\n        customer_status,\n        dbt_valid_from,\n        dbt_valid_to,\n        CASE \n            WHEN dbt_valid_to IS NULL THEN 'current'\n            ELSE 'historical'\n        END AS record_status\n    FROM dbt_db.snapshots.customer_snapshot\n)\n\nSELECT \n    customer_id,\n    customer_name,\n    customer_status,\n    record_status,\n    dbt_valid_from,\n    dbt_valid_to\nFROM snapshot_data\nORDER BY customer_id, dbt_valid_from", "relation_name": "dbt_db.dbt_schema_snapshot_data.customer_activity", "batch_results": null}, {"status": "success", "timing": [{"name": "compile", "started_at": "2025-10-20T06:54:55.944756Z", "completed_at": "2025-10-20T06:54:55.946203Z"}, {"name": "execute", "started_at": "2025-10-20T06:54:55.946203Z", "completed_at": "2025-10-20T06:55:01.358708Z"}], "thread_id": "Thread-10 (worker)", "execution_time": 5.415387392044067, "adapter_response": {"_message": "SUCCESS 1", "code": "SUCCESS", "rows_affected": 1, "query_id": "01bfd4be-3202-0771-0010-8a1200033406"}, "message": "SUCCESS 1", "failures": null, "unique_id": "model.data_pipeline.int_order_items", "compiled": true, "compiled_code": "select\n    line_item.order_item_key,\n    line_item.part_key,\n    line_item.line_number,\n    line_item.extended_price,\n    orders.order_key,\n    orders.customer_key,\n    orders.order_date,\n    \n    (-1 * line_item.extended_price * line_item.discount_percentage)::decimal(16, 2)\n as item_discount_amount\nfrom\n    dbt_db.dbt_schema.stg_tpch_orders as orders\njoin\n    dbt_db.dbt_schema.stg_tpch_line_items as line_item\n        on orders.order_key = line_item.order_key\norder by\n    orders.order_date", "relation_name": "dbt_db.dbt_schema.int_order_items", "batch_results": null}, {"status": "success", "timing": [{"name": "compile", "started_at": "2025-10-20T06:55:01.362765Z", "completed_at": "2025-10-20T06:55:01.366769Z"}, {"name": "execute", "started_at": "2025-10-20T06:55:01.366769Z", "completed_at": "2025-10-20T06:55:02.235312Z"}], "thread_id": "Thread-2 (worker)", "execution_time": 0.8735466003417969, "adapter_response": {"_message": "SUCCESS 1", "code": "SUCCESS", "rows_affected": 1, "query_id": "01bfd4bf-3202-077f-0010-8a1200034462"}, "message": "SUCCESS 1", "failures": null, "unique_id": "model.data_pipeline.int_order_items_summary", "compiled": true, "compiled_code": "select \n    order_key,\n    sum(extended_price) as gross_item_sales_amount,\n    sum(item_discount_amount) as item_discount_amount\nfrom\n    dbt_db.dbt_schema.int_order_items\ngroup by\n    order_key", "relation_name": "dbt_db.dbt_schema.int_order_items_summary", "batch_results": null}, {"status": "success", "timing": [{"name": "compile", "started_at": "2025-10-20T06:54:56.867261Z", "completed_at": "2025-10-20T06:54:56.869896Z"}, {"name": "execute", "started_at": "2025-10-20T06:54:56.869896Z", "completed_at": "2025-10-20T06:55:02.238193Z"}], "thread_id": "Thread-4 (worker)", "execution_time": 5.373022794723511, "adapter_response": {"_message": "SUCCESS 0", "code": "SUCCESS", "rows_affected": 0, "query_id": "01bfd4bf-3202-0771-0010-8a1200033422"}, "message": "SUCCESS 0", "failures": null, "unique_id": "snapshot.data_pipeline.customer_snapshot_check", "compiled": true, "compiled_code": "\n  \n\n  SELECT\n      customer_id,\n      customer_name,\n      customer_status\n  FROM dbt_db.dbt_schema.customers\n", "relation_name": "dbt_db.snapshots.customer_snapshot_check", "batch_results": null}, {"status": "pass", "timing": [{"name": "compile", "started_at": "2025-10-20T06:55:02.240823Z", "completed_at": "2025-10-20T06:55:02.256232Z"}, {"name": "execute", "started_at": "2025-10-20T06:55:02.257244Z", "completed_at": "2025-10-20T06:55:02.584836Z"}], "thread_id": "Thread-5 (worker)", "execution_time": 0.3440134525299072, "adapter_response": {"_message": "SUCCESS 1", "code": "SUCCESS", "rows_affected": 1, "query_id": "01bfd4bf-3202-0789-0010-8a12000353ba"}, "message": null, "failures": 0, "unique_id": "test.data_pipeline.not_null_customer_snapshot_check_customer_id.14c11eab32", "compiled": true, "compiled_code": "\n    \n    \n\n\n\nselect customer_id\nfrom dbt_db.snapshots.customer_snapshot_check\nwhere customer_id is null\n\n\n", "relation_name": null, "batch_results": null}, {"status": "success", "timing": [{"name": "compile", "started_at": "2025-10-20T06:55:02.593859Z", "completed_at": "2025-10-20T06:55:02.599870Z"}, {"name": "execute", "started_at": "2025-10-20T06:55:02.599870Z", "completed_at": "2025-10-20T06:55:03.551588Z"}], "thread_id": "Thread-8 (worker)", "execution_time": 0.9632401466369629, "adapter_response": {"_message": "SUCCESS 1", "code": "SUCCESS", "rows_affected": 1, "query_id": "01bfd4bf-3202-0771-0010-8a120003342a"}, "message": "SUCCESS 1", "failures": null, "unique_id": "model.data_pipeline.historical_customers", "compiled": true, "compiled_code": "SELECT \n    customer_id,\n    customer_name,\n    customer_status,\n    dbt_valid_from,\n    dbt_valid_to\nFROM dbt_db.snapshots.customer_snapshot_check\nWHERE dbt_valid_to IS NOT NULL\nORDER BY customer_id, dbt_valid_from", "relation_name": "dbt_db.dbt_schema_snapshot_data.historical_customers", "batch_results": null}, {"status": "success", "timing": [{"name": "compile", "started_at": "2025-10-20T06:55:02.240823Z", "completed_at": "2025-10-20T06:55:02.240823Z"}, {"name": "execute", "started_at": "2025-10-20T06:55:02.240823Z", "completed_at": "2025-10-20T06:55:03.624092Z"}], "thread_id": "Thread-3 (worker)", "execution_time": 1.3832683563232422, "adapter_response": {"_message": "SUCCESS 1", "code": "SUCCESS", "rows_affected": 1, "query_id": "01bfd4bf-3202-0771-0010-8a1200033426"}, "message": "SUCCESS 1", "failures": null, "unique_id": "model.data_pipeline.fct_orders", "compiled": true, "compiled_code": "select\n    orders.*,\n    order_item_summary.gross_item_sales_amount,\n    order_item_summary.item_discount_amount\nfrom\n    dbt_db.dbt_schema.stg_tpch_orders as orders\njoin\n    dbt_db.dbt_schema.int_order_items_summary as order_item_summary\n        on orders.order_key = order_item_summary.order_key\norder by order_date", "relation_name": "dbt_db.dbt_schema.fct_orders", "batch_results": null}, {"status": "pass", "timing": [{"name": "compile", "started_at": "2025-10-20T06:55:03.646337Z", "completed_at": "2025-10-20T06:55:03.674590Z"}, {"name": "execute", "started_at": "2025-10-20T06:55:03.675074Z", "completed_at": "2025-10-20T06:55:04.051575Z"}], "thread_id": "Thread-2 (worker)", "execution_time": 0.4083397388458252, "adapter_response": {"_message": "SUCCESS 1", "code": "SUCCESS", "rows_affected": 1, "query_id": "01bfd4bf-3202-077f-0010-8a120003446e"}, "message": null, "failures": 0, "unique_id": "test.data_pipeline.fct_orders_date_valid", "compiled": true, "compiled_code": "select\n    *\nfrom\n    dbt_db.dbt_schema.fct_orders\nwhere\n    date(order_date) > CURRENT_DATE()\n    or date(order_date) < date('1990-01-01')", "relation_name": null, "batch_results": null}, {"status": "pass", "timing": [{"name": "compile", "started_at": "2025-10-20T06:55:03.661602Z", "completed_at": "2025-10-20T06:55:03.675074Z"}, {"name": "execute", "started_at": "2025-10-20T06:55:03.681281Z", "completed_at": "2025-10-20T06:55:04.053606Z"}], "thread_id": "Thread-1 (worker)", "execution_time": 0.40825867652893066, "adapter_response": {"_message": "SUCCESS 1", "code": "SUCCESS", "rows_affected": 1, "query_id": "01bfd4bf-3202-0771-0010-8a120003342e"}, "message": null, "failures": 0, "unique_id": "test.data_pipeline.not_null_fct_orders_order_key.6a6f83ab15", "compiled": true, "compiled_code": "\n    \n    \n\n\n\nselect order_key\nfrom dbt_db.dbt_schema.fct_orders\nwhere order_key is null\n\n\n", "relation_name": null, "batch_results": null}, {"status": "pass", "timing": [{"name": "compile", "started_at": "2025-10-20T06:55:03.659089Z", "completed_at": "2025-10-20T06:55:03.675074Z"}, {"name": "execute", "started_at": "2025-10-20T06:55:03.686361Z", "completed_at": "2025-10-20T06:55:04.054722Z"}], "thread_id": "Thread-4 (worker)", "execution_time": 0.4104881286621094, "adapter_response": {"_message": "SUCCESS 1", "code": "SUCCESS", "rows_affected": 1, "query_id": "01bfd4bf-3202-0771-0010-8a1200033432"}, "message": null, "failures": 0, "unique_id": "test.data_pipeline.fct_orders_discount", "compiled": true, "compiled_code": "select\n    *\nfrom\n    dbt_db.dbt_schema.fct_orders\nwhere\n    item_discount_amount > 0", "relation_name": null, "batch_results": null}, {"status": "pass", "timing": [{"name": "compile", "started_at": "2025-10-20T06:55:03.646337Z", "completed_at": "2025-10-20T06:55:03.672841Z"}, {"name": "execute", "started_at": "2025-10-20T06:55:03.675074Z", "completed_at": "2025-10-20T06:55:04.057021Z"}], "thread_id": "Thread-6 (worker)", "execution_time": 0.4157869815826416, "adapter_response": {"_message": "SUCCESS 1", "code": "SUCCESS", "rows_affected": 1, "query_id": "01bfd4bf-3202-0771-0010-8a1200033436"}, "message": null, "failures": 0, "unique_id": "test.data_pipeline.accepted_values_fct_orders_status_code__P__O__F.2c062f3048", "compiled": true, "compiled_code": "\n    \n    \n\nwith all_values as (\n\n    select\n        status_code as value_field,\n        count(*) as n_records\n\n    from dbt_db.dbt_schema.fct_orders\n    group by status_code\n\n)\n\nselect *\nfrom all_values\nwhere value_field not in (\n    'P','O','F'\n)\n\n\n", "relation_name": null, "batch_results": null}, {"status": "pass", "timing": [{"name": "compile", "started_at": "2025-10-20T06:55:03.663312Z", "completed_at": "2025-10-20T06:55:03.684239Z"}, {"name": "execute", "started_at": "2025-10-20T06:55:03.689524Z", "completed_at": "2025-10-20T06:55:04.129122Z"}], "thread_id": "Thread-5 (worker)", "execution_time": 0.4827849864959717, "adapter_response": {"_message": "SUCCESS 1", "code": "SUCCESS", "rows_affected": 1, "query_id": "01bfd4bf-3202-0789-0010-8a12000353be"}, "message": null, "failures": 0, "unique_id": "test.data_pipeline.unique_fct_orders_order_key.f5e7a90273", "compiled": true, "compiled_code": "\n    \n    \n\nselect\n    order_key as unique_field,\n    count(*) as n_records\n\nfrom dbt_db.dbt_schema.fct_orders\nwhere order_key is not null\ngroup by order_key\nhaving count(*) > 1\n\n\n", "relation_name": null, "batch_results": null}, {"status": "success", "timing": [{"name": "compile", "started_at": "2025-10-20T06:55:02.590351Z", "completed_at": "2025-10-20T06:55:02.595862Z"}, {"name": "execute", "started_at": "2025-10-20T06:55:02.595862Z", "completed_at": "2025-10-20T06:55:04.133781Z"}], "thread_id": "Thread-7 (worker)", "execution_time": 1.545433521270752, "adapter_response": {"_message": "SUCCESS 1", "code": "SUCCESS", "rows_affected": 1, "query_id": "01bfd4bf-3202-077f-0010-8a120003446a"}, "message": "SUCCESS 1", "failures": null, "unique_id": "model.data_pipeline.current_customers", "compiled": true, "compiled_code": "SELECT \n    customer_id,\n    customer_name,\n    customer_status,\n    dbt_valid_from,\n    dbt_valid_to\nFROM dbt_db.snapshots.customer_snapshot_check\nWHERE dbt_valid_to IS NULL", "relation_name": "dbt_db.dbt_schema_snapshot_data.current_customers", "batch_results": null}, {"status": "pass", "timing": [{"name": "compile", "started_at": "2025-10-20T06:55:03.663312Z", "completed_at": "2025-10-20T06:55:03.675074Z"}, {"name": "execute", "started_at": "2025-10-20T06:55:03.682337Z", "completed_at": "2025-10-20T06:55:04.921041Z"}], "thread_id": "Thread-9 (worker)", "execution_time": 1.2747046947479248, "adapter_response": {"_message": "SUCCESS 1", "code": "SUCCESS", "rows_affected": 1, "query_id": "01bfd4bf-3202-0789-0010-8a12000353c2"}, "message": null, "failures": 0, "unique_id": "test.data_pipeline.relationships_fct_orders_order_key__order_key__ref_stg_tpch_orders_.05b89e79ce", "compiled": true, "compiled_code": "\n    \n    \n\nwith child as (\n    select order_key as from_field\n    from dbt_db.dbt_schema.fct_orders\n    where order_key is not null\n),\n\nparent as (\n    select order_key as to_field\n    from dbt_db.dbt_schema.stg_tpch_orders\n)\n\nselect\n    from_field\n\nfrom child\nleft join parent\n    on child.from_field = parent.to_field\n\nwhere parent.to_field is null\n\n\n", "relation_name": null, "batch_results": null}], "elapsed_time": 20.37654137611389, "args": {"log_format": "default", "populate_cache": true, "quiet": false, "indirect_selection": "eager", "select": [], "invocation_command": "dbt build", "upload_to_artifacts_ingest_api": false, "exclude_resource_types": [], "use_colors": true, "version_check": true, "show_resource_report": false, "vars": {}, "exclude": [], "show": false, "skip_nodes_if_on_run_start_fails": false, "empty": false, "introspect": true, "state_modified_compare_more_unrendered_values": false, "show_all_deprecations": false, "require_batched_execution_for_custom_microbatch_strategy": false, "partial_parse_file_diff": true, "log_path": "C:\\Users\\lenovo\\data_pipeline\\logs", "project_dir": "C:\\Users\\lenovo\\data_pipeline", "log_format_file": "debug", "macro_debugging": false, "log_level": "info", "export_saved_queries": false, "favor_state": false, "strict_mode": false, "which": "build", "include_saved_query": false, "require_yaml_configuration_for_mf_time_spines": false, "partial_parse": true, "source_freshness_run_project_hooks": true, "resource_types": [], "defer": false, "write_json": true, "cache_selected_only": false, "static_parser": true, "send_anonymous_usage_stats": true, "validate_macro_args": false, "state_modified_compare_vars": false, "warn_error_options": {"error": [], "warn": [], "silence": []}, "print": true, "require_generic_test_arguments_property": false, "require_resource_names_without_spaces": true, "log_level_file": "debug", "profiles_dir": "C:\\Users\\lenovo\\.dbt", "use_fast_test_edges": false, "log_file_max_bytes": 10485760, "printer_width": 80, "require_all_warnings_handled_by_warn_error": false, "use_colors_file": true, "require_explicit_package_overrides_for_builtin_materializations": true, "require_nested_cumulative_type_params": false}}